{
  "generated": "2026-03-26T07:00:00+11:00",
  "functions": [
    {
      "name": "Sales Engine",
      "owner": "Rye",
      "status": "amber",
      "constraint": "DC capacity - only Anthony active Mon/Tue, Rye coaching-focused",
      "key_metric": "Close Rate: 36% (Anthony) / 90% (Rye)",
      "highest_leverage_task": "Get Tom on DCs & coach Anthony's E-score up 1 point",
      "team": ["Rye", "Anthony", "Tom (onboarding)"]
    },
    {
      "name": "Mentor Journey",
      "owner": "TBD",
      "status": "red",
      "constraint": "No single owner - split across Harry/Brodie/mentors",
      "key_metric": "Session gap avg: needs measurement",
      "highest_leverage_task": "Assign owner & connect Fireflies to member records",
      "team": ["Mentors", "Brodie (activation)"]
    },
    {
      "name": "Member Experience",
      "owner": "Brodie & Norri",
      "status": "amber",
      "constraint": "63% of churned families never got a mentor - activation gap",
      "key_metric": "Close-to-W1 conversion: ~59%",
      "highest_leverage_task": "Tighten post-close activation to <7 days from close to W1",
      "team": ["Brodie", "Norri", "Microowners"]
    },
    {
      "name": "Brand & Content",
      "owner": "Harry",
      "status": "green",
      "constraint": "Content creation bottlenecked on Harry's time",
      "key_metric": "18 newsletters drafted, content engine skill live",
      "highest_leverage_task": "Batch-produce content from newsletters & repurpose",
      "team": ["Harry", "Leo"]
    }
  ]
}
