{
  "generated": "2026-04-20T06:30:04.831317",
  "paused_subs": [
    {
      "name": "Judy Lacey (Son Jack)",
      "email": "phudyjillips@hotmail.com",
      "amount": 664.0,
      "resumes_at": "indefinite",
      "stripe_url": "https://dashboard.stripe.com/subscriptions/sub_1TEh802mA5zLxyK8HK6eCH9I",
      "hs_url": "",
      "hs_member_status": "Active Sessions"
    },
    {
      "name": "Brooke Miranda",
      "email": "brookegm78@yahoo.com.au",
      "amount": 940.0,
      "resumes_at": "indefinite",
      "stripe_url": "https://dashboard.stripe.com/subscriptions/sub_1TCG1m2mA5zLxyK819BJSq9C",
      "hs_url": "",
      "hs_member_status": "Active Sessions"
    },
    {
      "name": "Aeshlie Wheeler",
      "email": "Operations@tastalent.com",
      "amount": 904.0,
      "resumes_at": "indefinite",
      "stripe_url": "https://dashboard.stripe.com/subscriptions/sub_1TAJET2mA5zLxyK8ffd263uN",
      "hs_url": "",
      "hs_member_status": "Active Sessions"
    },
    {
      "name": "Natalie Brennan",
      "email": "nbrennan@gelatissimo.com.au",
      "amount": 1808.0,
      "resumes_at": "indefinite",
      "stripe_url": "https://dashboard.stripe.com/subscriptions/sub_1Sylmv2mA5zLxyK8jXOFKBwl",
      "hs_url": "",
      "hs_member_status": "Active Sessions"
    },
    {
      "name": "Emily Greaves",
      "email": "em-greaves@hotmail.com",
      "amount": 232.0,
      "resumes_at": "indefinite",
      "stripe_url": "https://dashboard.stripe.com/subscriptions/sub_1Sjd6L2mA5zLxyK8XzL49PU9",
      "hs_url": "",
      "hs_member_status": "Active Sessions"
    },
    {
      "name": "Taya Wear",
      "email": "mitchlovestaya@gmail.com",
      "amount": 1808.0,
      "resumes_at": "2026-05-18",
      "stripe_url": "https://dashboard.stripe.com/subscriptions/sub_1SdNL92mA5zLxyK8v58BTnyP",
      "hs_url": "",
      "hs_member_status": "Active Sessions"
    },
    {
      "name": "Melissa Angell",
      "email": "mel@directelectricalsolutions.com.au",
      "amount": 2856.0,
      "resumes_at": "indefinite",
      "stripe_url": "https://dashboard.stripe.com/subscriptions/sub_1SUvxI2mA5zLxyK8LrSQiiNK",
      "hs_url": "",
      "hs_member_status": "Active Sessions"
    },
    {
      "name": "Kate O'Sullivan",
      "email": "kateos9785@gmail.com",
      "amount": 2001.32,
      "resumes_at": "indefinite",
      "stripe_url": "https://dashboard.stripe.com/subscriptions/sub_1Rt6Je2mA5zLxyK8ylzWu3ce",
      "hs_url": "",
      "hs_member_status": "Active Sessions"
    }
  ],
  "total_count": 8
}